coco_loader/__init__.py
coco_loader/bases.py
coco_loader/common.py
coco_loader/imagecaptioning.py
coco_loader/keypointdetection.py
coco_loader/objectdetection.py
coco_loader/panopticsegmentation.py
coco_loader-0.1.1.dist-info/LICENSE
coco_loader-0.1.1.dist-info/WHEEL
coco_loader-0.1.1.dist-info/METADATA
coco_loader-0.1.1.dist-info/RECORD
