Metadata-Version: 2.1
Name: coco-loader
Version: 0.1.1
Summary: COCO dataset loader.
Home-page: https://github.com/jinhyuckcha/coco-loader
License: MIT
Author: Jinhyuck Cha
Author-email: jhcha@superb-ai.com
Maintainer: Jinhyuck Cha
Maintainer-email: jhcha@superb-ai.com
Requires-Python: >=3.7,<4.0
Classifier: License :: OSI Approved :: MIT License
Classifier: Programming Language :: Python :: 3
Classifier: Programming Language :: Python :: 3.7
Classifier: Programming Language :: Python :: 3.8
Classifier: Programming Language :: Python :: 3.9
Classifier: Programming Language :: Python :: 3.10
Classifier: Programming Language :: Python :: 3.11
Requires-Dist: dataclasses-json (>=0.5.4,<0.6.0)
Project-URL: Bug Tracker, https://github.com/jinhyuckcha/coco-loader/issues
Project-URL: Repository, https://github.com/jinhyuckcha/coco-loader
